data_process.py
segmenter.py
train.py
disaster_new_pos-1.0.0.dev1.dist-info/DESCRIPTION.rst
disaster_new_pos-1.0.0.dev1.dist-info/METADATA
disaster_new_pos-1.0.0.dev1.dist-info/RECORD
disaster_new_pos-1.0.0.dev1.dist-info/WHEEL
disaster_new_pos-1.0.0.dev1.dist-info/metadata.json
disaster_new_pos-1.0.0.dev1.dist-info/top_level.txt
