Metadata-Version: 2.0
Name: disaster-new-pos
Version: 1.0.0.dev1
Summary: disaster news domain entity recognition
Home-page: UNKNOWN
Author: mario
Author-email: 503373015@qq.com
License: MIT
Keywords: disaster news pos
Platform: UNKNOWN
